<?xml version="1.0" encoding="UTF-8" standalone="yes"?>
<KeyValueMapOperations async="false" continueOnError="false" enabled="true" name="Credenciales-Semantikos" mapIdentifier="CredencialesSemantikos">
  <DisplayName>Credenciales-Semantikos</DisplayName>
  <Properties/>
  <ExclusiveCache>false</ExclusiveCache>
  <ExpiryTimeInSecs>300</ExpiryTimeInSecs>
  <Get assignTo="username" index="1">
    <Key>
      <Parameter>username</Parameter>
    </Key>
  </Get>
  <Get assignTo="password" index="1">
    <Key>
      <Parameter>password</Parameter>
    </Key>
  </Get>
  <Scope>environment</Scope>
</KeyValueMapOperations>
